geoseer/__init__.py
geoseer/crs_transform.py
geoseer/nav_data.py
geoseer/poly2fpq.py
geoseer/poly_frac_interp_processing.py
geoseer-0.0a0.dev1.dist-info/LICENSE
geoseer-0.0a0.dev1.dist-info/METADATA
geoseer-0.0a0.dev1.dist-info/WHEEL
geoseer-0.0a0.dev1.dist-info/top_level.txt
geoseer-0.0a0.dev1.dist-info/RECORD
