Metadata-Version: 2.1
Name: geoseer
Version: 0.0a0.dev1
Summary: "A collection of scripts for geoscience applications"
Home-page: UNKNOWN
Author: "Simon Oldfield"
License: Apache License Version 2.0
Keywords: python3,geoscience,geology
Platform: UNKNOWN
Classifier: Programming Language :: Python :: 3.8
Classifier: Programming Language :: Python :: 3
Classifier: License :: OSI Approved :: Apache Software License
Classifier: Operating System :: OS Independent
Classifier: Natural Language :: English
Classifier: Topic :: Scientific/Engineering
Requires-Dist: numpy
Requires-Dist: shapely
Requires-Dist: matplotlib
